LICENCE.txt
README.md
setup.py
yacine_47_rocket/__init__.py
yacine_47_rocket/rocket.py
yacine_47_rocket.egg-info/PKG-INFO
yacine_47_rocket.egg-info/SOURCES.txt
yacine_47_rocket.egg-info/dependency_links.txt
yacine_47_rocket.egg-info/top_level.txt