Metadata-Version: 2.1
Name: yacine-47-rocket
Version: 1.0.0
Summary: An awesome package that does something with rockets and shuttles
Home-page: http://pypi.python.org/pypi/yacine_47_rocket/
Author: Yassine DRISS
Author-email: y.driss@esi-sba.dz
License: LICENSE.txt
License-File: LICENCE.txt
